spared/__init__.py
spared/gtftools.py
spared/PublicDatabase/README_template.md
spared/configs/10xgenomic_human_brain.json
spared/configs/10xgenomic_human_breast_cancer.json
spared/configs/10xgenomic_mouse_brain_coronal.json
spared/configs/10xgenomic_mouse_brain_sagittal_anterior.json
spared/configs/10xgenomic_mouse_brain_sagittal_posterior.json
spared/configs/abalo_human_squamous_cell_carcinoma.json
spared/configs/add_hex_geometry.py
spared/configs/add_organism.py
spared/configs/batiuk_human_brain.json
spared/configs/erickson_human_prostate_cancer_p1.json
spared/configs/erickson_human_prostate_cancer_p2.json
spared/configs/fan_mouse_brain_coronal.json
spared/configs/fan_mouse_olfatory_bulb.json
spared/configs/hudson_human_brain.json
spared/configs/mirzazadeh_human_colon_p1.json
spared/configs/mirzazadeh_human_colon_p2.json
spared/configs/mirzazadeh_human_pediatric_brain_tumor_p1.json
spared/configs/mirzazadeh_human_pediatric_brain_tumor_p2.json
spared/configs/mirzazadeh_human_prostate_cancer.json
spared/configs/mirzazadeh_human_small_intestine.json
spared/configs/mirzazadeh_mouse_bone.json
spared/configs/mirzazadeh_mouse_brain.json
spared/configs/mirzazadeh_mouse_brain_p1.json
spared/configs/mirzazadeh_mouse_brain_p2.json
spared/configs/parigi_mouse_intestine.json
spared/configs/vicari_human_striatium.json
spared/configs/vicari_mouse_brain.json
spared/configs/villacampa_kidney_organoid.json
spared/configs/villacampa_lung_organoid.json
spared/configs/villacampa_mouse_brain.json
spared/data/annotations/gencode.v43.basic.annotation.gtf.gz
spared/data/annotations/gencode.vM33.basic.annotation.gtf.gz
spared/data/annotations/gene_length.txt
spared/data/annotations/gene_length_mouse.txt
spared/data/annotations/mapping_HUGO_2_Ensemble.txt
spared/data/annotations/mart_export.txt
spared/data/annotations/old_gencode.v43.basic.annotation.gtf.gz
spared/data/annotations/old_gencode.vM33.basic.annotation.gtf.gz
spared/dataloaders/__init__.py
spared/dataloaders/dataloaders.py
spared-2.2.1.dist-info/LICENSE.txt
spared-2.2.1.dist-info/METADATA
spared-2.2.1.dist-info/WHEEL
spared-2.2.1.dist-info/top_level.txt
spared-2.2.1.dist-info/RECORD
