Metadata-Version: 2.1
Name: spared
Version: 2.2.1
Summary: SpaRED and Spackle library
Home-page: https://github.com/BCV-Uniandes/SpaRED/tree/main
Author: Daniela Vega
Author-email: d.vegaa@uniandes.edu.co
License: UNKNOWN
Project-URL: Bug Reports, https://github.com/BCV-Uniandes/SpaRED/issues
Project-URL: Source, https://github.com/BCV-Uniandes/SpaRED/
Platform: UNKNOWN
Classifier: Development Status :: 3 - Alpha
Classifier: Programming Language :: Python :: 3
Classifier: License :: OSI Approved :: MIT License
Classifier: Operating System :: OS Independent
Requires-Python: >=3.7
